smiles/__init__.py
smiles/app.py
smiles/templates/input_form.html
smiles-0.0.0.dist-info/METADATA
smiles-0.0.0.dist-info/WHEEL
smiles-0.0.0.dist-info/RECORD
