Metadata-Version: 2.1
Name: smiles
Version: 0.0.0
Summary: 
License: MIT
Author: Alán F. Muñoz
Author-email: amunozgo@broadinstitute.org
Requires-Python: >=3.11,<4.0
Classifier: License :: OSI Approved :: MIT License
Classifier: Programming Language :: Python :: 3
Classifier: Programming Language :: Python :: 3.11
Classifier: Programming Language :: Python :: 3.12
Requires-Dist: Flask (>=3.0.2,<4.0.0)
